{"coins":{"Nicehash-Etchash":{"id":50,"tag":"NICEHASH","algorithm":"Etchash","block_time":1,"block_reward":1,"block_reward24":1,"last_block":0,"difficulty":1,"difficulty24":1,"nethash":5018571500200,"exchange_rate":0.00011807573777181896,"exchange_rate24":0.00016566070289131664,"exchange_rate_vol":0.8321141282109297,"exchange_rate_curr":"BTC","market_cap":"$0","estimated_rewards":"0.0","estimated_rewards24":"0.0","btc_revenue":"0.0","btc_revenue24":"0.0","profitability":0,"profitability24":0,"lagging":false,"timestamp":1672367951},"Nicehash-Ethash":{"id":15,"tag":"NICEHASH","algorithm":"Ethash","block_time":1,"block_reward":1,"block_reward24":1,"last_block":0,"difficulty":1,"difficulty24":1,"nethash":2892827330786,"exchange_rate":0.1383566489232497,"exchange_rate24":0.16840670402224855,"exchange_rate_vol":0.46069160601787107,"exchange_rate_curr":"BTC","market_cap":"$0","estimated_rewards":"0.0","estimated_rewards24":"0.0","btc_revenue":"0.0","btc_revenue24":"0.0","profitability":0,"profitability24":0,"lagging":false,"timestamp":1672367951},"EthereumPoW":{"id":353,"tag":"ETHW","algorithm":"Ethash","block_time":"13.2807","block_reward":2.0215173834295483,"block_reward24":2.019221277228868,"last_block":16226687,"difficulty":224778245449635.0,"difficulty24":223942929562851.84,"nethash":16925180558979,"exchange_rate":0.00017997444848093689,"exchange_rate24":0.00017887318954718708,"exchange_rate_vol":23.566979102924332,"exchange_rate_curr":"BTC","market_cap":"$322,105,866","estimated_rewards":"0.0","estimated_rewards24":"0.0","btc_revenue":"0.0","btc_revenue24":"0.0","profitability":0,"profitability24":0,"lagging":false,"timestamp":1672367991},"EthereumFair":{"id":355,"tag":"ETHF","algorithm":"Ethash","block_time":"13.3004","block_reward":2.0,"block_reward24":2.0046464896660985,"last_block":16221142,"difficulty":30562670495792.0,"difficulty24":30613897681043.34,"nethash":2297876041005,"exchange_rate":2.457617832600222e-05,"exchange_rate24":2.4711143896469357e-05,"exchange_rate_vol":4.648212639402923,"exchange_rate_curr":"BTC","market_cap":"$50,086,979","estimated_rewards":"0.0","estimated_rewards24":"0.0","btc_revenue":"0.0","btc_revenue24":"0.0","profitability":0,"profitability24":0,"lagging":false,"timestamp":1672367915},"Etho":{"id":306,"tag":"ETHO","algorithm":"Ethash","block_time":"13.5103","block_reward":0.3,"block_reward24":0.3000000000000033,"last_block":10736031,"difficulty":125595620189.0,"difficulty24":134070988693.61636,"nethash":9296286550,"exchange_rate":6.5e-07,"exchange_rate24":6.050634696755984e-07,"exchange_rate_vol":0.00188083,"exchange_rate_curr":"BTC","market_cap":"$862,592","estimated_rewards":"0.0","estimated_rewards24":"0.0","btc_revenue":"0.0","btc_revenue24":"0.0","profitability":0,"profitability24":0,"lagging":false,"timestamp":1672367902},"EtherGem":{"id":307,"tag":"EGEM","algorithm":"Ethash","block_time":"12.1265","block_reward":2.88,"block_reward24":2.8800000000000523,"last_block":12046289,"difficulty":225235137537.0,"difficulty24":241740506318.41183,"nethash":18573796028,"exchange_rate":1.44e-07,"exchange_rate24":1.4432768361582062e-07,"exchange_rate_vol":0.0385892039039,"exchange_rate_curr":"BTC","market_cap":"$46,599","estimated_rewards":"0.0","estimated_rewards24":"0.0","btc_revenue":"0.0","btc_revenue24":"0.0","profitability":0,"profitability24":0,"lagging":false,"timestamp":1672367903},"QuarkChain":{"id":318,"tag":"QKC","algorithm":"Ethash","block_time":"9.6833","block_reward":2.214784,"block_reward24":2.214784000000008,"last_block":11808120,"difficulty":238798720135.0,"difficulty24":239133138104.7735,"nethash":49321764302,"exchange_rate":4.4e-07,"exchange_rate24":4.39464033850488e-07,"exchange_rate_vol":2.20092704,"exchange_rate_curr":"BTC","market_cap":"$46,771,893","estimated_rewards":"0.0","estimated_rewards24":"0.0","btc_revenue":"0.0","btc_revenue24":"0.0","profitability":0,"profitability24":0,"lagging":false,"timestamp":1672367905},"Callisto":{"id":283,"tag":"CLO","algorithm":"Ethash","block_time":"12.7211","block_reward":38.932,"block_reward24":38.90627835051574,"last_block":11426398,"difficulty":4934796906799.0,"difficulty24":4766948155110.95,"nethash":387922184936,"exchange_rate":1.807270262101751e-07,"exchange_rate24":1.8334112347098634e-07,"exchange_rate_vol":3.9951084600242943,"exchange_rate_curr":"BTC","market_cap":"$9,319,908","estimated_rewards":"0.0","estimated_rewards24":"0.0","btc_revenue":"0.0","btc_revenue24":"0.0","profitability":0,"profitability24":0,"lagging":false,"timestamp":1672367913},"Ubiq":{"id":173,"tag":"UBQ","algorithm":"Ubqhash","block_time":"21.0","block_reward":1.5,"block_reward24":1.5,"last_block":3196932,"difficulty":1239652355464.0,"difficulty24":1204901319722.548,"nethash":59031064545,"exchange_rate":1.79e-06,"exchange_rate24":1.7366290550070489e-06,"exchange_rate_vol":0.0015931,"exchange_rate_curr":"BTC","market_cap":"$1,266,817","estimated_rewards":"0.0","estimated_rewards24":"0.0","btc_revenue":"0.0","btc_revenue24":"0.0","profitability":0,"profitability24":0,"lagging":false,"timestamp":1672367895},"Expanse":{"id":154,"tag":"EXP","algorithm":"Ethash","block_time":"21.0","block_reward":4.0,"block_reward24":4.0,"last_block":7181173,"difficulty":613612813692.0,"difficulty24":581394430260.0626,"nethash":29219657794,"exchange_rate":2.4e-07,"exchange_rate24":2.3913963328631905e-07,"exchange_rate_vol":0.03252107,"exchange_rate_curr":"BTC","market_cap":"$74,962","estimated_rewards":"0.0","estimated_rewards24":"0.0","btc_revenue":"0.0","btc_revenue24":"0.0","profitability":0,"profitability24":0,"lagging":false,"timestamp":1672367892},"EthereumClassic":{"id":162,"tag":"ETC","algorithm":"Etchash","block_time":"13.0524","block_reward":2.4832,"block_reward24":2.4831999999999623,"last_block":16638353,"difficulty":1.685631039576881e+15,"difficulty24":1617771174964903.8,"nethash":129143378963016,"exchange_rate":0.000939,"exchange_rate24":0.0009385444287729168,"exchange_rate_vol":48.73039184,"exchange_rate_curr":"BTC","market_cap":"$2,163,158,937","estimated_rewards":"0.0","estimated_rewards24":"0.0","btc_revenue":"0.0","btc_revenue24":"0.0","profitability":0,"profitability24":0,"lagging":false,"timestamp":1672367893}}}