{"coins":{"Nicehash-Ethash":{"id":15,"tag":"NICEHASH","algorithm":"Ethash","block_time":1,"block_reward":1,"block_reward24":1,"last_block":0,"difficulty":1,"difficulty24":1,"nethash":2888980155218,"exchange_rate":0.14034752334374162,"exchange_rate24":0.1719255662996681,"exchange_rate_vol":0.5049301144152718,"exchange_rate_curr":"BTC","market_cap":"$0","estimated_rewards":"0.0","estimated_rewards24":"0.0","btc_revenue":"0.0","btc_revenue24":"0.0","profitability":0,"profitability24":0,"lagging":false,"timestamp":1676429531},"Nicehash-Etchash":{"id":50,"tag":"NICEHASH","algorithm":"Etchash","block_time":1,"block_reward":1,"block_reward24":1,"last_block":0,"difficulty":1,"difficulty24":1,"nethash":4132590732812,"exchange_rate":0.00011732819063842646,"exchange_rate24":0.000145298259652764,"exchange_rate_vol":0.6022105533924719,"exchange_rate_curr":"BTC","market_cap":"$0","estimated_rewards":"0.0","estimated_rewards24":"0.0","btc_revenue":"0.0","btc_revenue24":"0.0","profitability":0,"profitability24":0,"lagging":false,"timestamp":1676429530},"Etho":{"id":306,"tag":"ETHO","algorithm":"Ethash","block_time":"11.8766","block_reward":0.3,"block_reward24":0.3000000000000034,"last_block":11047949,"difficulty":165058757079.0,"difficulty24":141615773482.8892,"nethash":13897812259,"exchange_rate":5.9e-07,"exchange_rate24":5.790909090909179e-07,"exchange_rate_vol":0.02533628,"exchange_rate_curr":"BTC","market_cap":"$1,040,125","estimated_rewards":"0.0","estimated_rewards24":"0.0","btc_revenue":"0.0","btc_revenue24":"0.0","profitability":0,"profitability24":0,"lagging":false,"timestamp":1676429427},"EtherGem":{"id":307,"tag":"EGEM","algorithm":"Ethash","block_time":"12.0377","block_reward":2.88,"block_reward24":2.8800000000000523,"last_block":12380788,"difficulty":175192398596.0,"difficulty24":193934661335.29553,"nethash":14553643851,"exchange_rate":1.06e-07,"exchange_rate24":1.0780419580419558e-07,"exchange_rate_vol":0.0309265385811,"exchange_rate_curr":"BTC","market_cap":"$45,568","estimated_rewards":"0.0","estimated_rewards24":"0.0","btc_revenue":"0.0","btc_revenue24":"0.0","profitability":0,"profitability24":0,"lagging":false,"timestamp":1676429422},"EthereumPoW":{"id":353,"tag":"ETHW","algorithm":"Ethash","block_time":"13.2168","block_reward":2.0045936249904774,"block_reward24":2.003805613407682,"last_block":16531771,"difficulty":220470065655871.0,"difficulty24":215725952696272.28,"nethash":16681047277394,"exchange_rate":0.00016767797050569125,"exchange_rate24":0.00016683633306115183,"exchange_rate_vol":32.2973711707688,"exchange_rate_curr":"BTC","market_cap":"$398,906,671","estimated_rewards":"0.0","estimated_rewards24":"0.0","btc_revenue":"0.0","btc_revenue24":"0.0","profitability":0,"profitability24":0,"lagging":false,"timestamp":1676429508},"EthereumFair":{"id":355,"tag":"ETHF","algorithm":"Ethash","block_time":"13.232","block_reward":2.0,"block_reward24":2.0024651635715482,"last_block":16523405,"difficulty":19875956898492.0,"difficulty24":19702212827609.363,"nethash":1502112824855,"exchange_rate":1.5150285297874744e-05,"exchange_rate24":1.527515700694552e-05,"exchange_rate_vol":1.526950251119584,"exchange_rate_curr":"BTC","market_cap":"$41,017,827","estimated_rewards":"0.0","estimated_rewards24":"0.0","btc_revenue":"0.0","btc_revenue24":"0.0","profitability":0,"profitability24":0,"lagging":false,"timestamp":1676429543},"QuarkChain":{"id":318,"tag":"QKC","algorithm":"Ethash","block_time":"9.8063","block_reward":2.214784,"block_reward24":2.214784000000008,"last_block":12224338,"difficulty":311882720490.0,"difficulty24":325779094023.48517,"nethash":63608643523,"exchange_rate":4.6e-07,"exchange_rate24":4.5493016759776214e-07,"exchange_rate_vol":1.45030233,"exchange_rate_curr":"BTC","market_cap":"$64,957,822","estimated_rewards":"0.0","estimated_rewards24":"0.0","btc_revenue":"0.0","btc_revenue24":"0.0","profitability":0,"profitability24":0,"lagging":false,"timestamp":1676429428},"Callisto":{"id":283,"tag":"CLO","algorithm":"Ethash","block_time":"12.7941","block_reward":38.932,"block_reward24":38.92553810623573,"last_block":11740091,"difficulty":3661748325311.0,"difficulty24":3573068257620.538,"nethash":286206010998,"exchange_rate":1.4479954827780915e-07,"exchange_rate24":1.467291224490283e-07,"exchange_rate_vol":0.053109054877816204,"exchange_rate_curr":"BTC","market_cap":"$9,919,666","estimated_rewards":"0.0","estimated_rewards24":"0.0","btc_revenue":"0.0","btc_revenue24":"0.0","profitability":0,"profitability24":0,"lagging":false,"timestamp":1676429419},"Ubiq":{"id":173,"tag":"UBQ","algorithm":"Ubqhash","block_time":"21.0","block_reward":1.5,"block_reward24":1.5,"last_block":3383771,"difficulty":1273000296720.0,"difficulty24":1276678178869.6086,"nethash":60619061748,"exchange_rate":1.48e-06,"exchange_rate24":1.4849441340782364e-06,"exchange_rate_vol":0.00656206,"exchange_rate_curr":"BTC","market_cap":"$1,391,438","estimated_rewards":"0.0","estimated_rewards24":"0.0","btc_revenue":"0.0","btc_revenue24":"0.0","profitability":0,"profitability24":0,"lagging":false,"timestamp":1676429534},"Expanse":{"id":154,"tag":"EXP","algorithm":"Ethash","block_time":"21.0","block_reward":4.0,"block_reward24":4.0,"last_block":7368109,"difficulty":540658060348.0,"difficulty24":541412977770.17487,"nethash":25745621921,"exchange_rate":2.2e-07,"exchange_rate24":2.142877094972042e-07,"exchange_rate_vol":0.01805433,"exchange_rate_curr":"BTC","market_cap":"$91,284","estimated_rewards":"0.0","estimated_rewards24":"0.0","btc_revenue":"0.0","btc_revenue24":"0.0","profitability":0,"profitability24":0,"lagging":false,"timestamp":1676429532},"EthereumClassic":{"id":162,"tag":"ETC","algorithm":"Etchash","block_time":"13.346","block_reward":2.4832,"block_reward24":2.4831999999999614,"last_block":16944917,"difficulty":1.633044373061271e+15,"difficulty24":1688216361600041.5,"nethash":122362083999795,"exchange_rate":0.000947,"exchange_rate24":0.0009462081005586544,"exchange_rate_vol":47.11966061,"exchange_rate_curr":"BTC","market_cap":"$2,910,469,871","estimated_rewards":"0.0","estimated_rewards24":"0.0","btc_revenue":"0.0","btc_revenue24":"0.0","profitability":0,"profitability24":0,"lagging":false,"timestamp":1676429533}}}