{"coins":{"Nicehash-Ethash":{"id":15,"tag":"NICEHASH","algorithm":"Ethash","block_time":1,"block_reward":1,"block_reward24":1,"last_block":0,"difficulty":1,"difficulty24":1,"nethash":18642283985,"exchange_rate":0.009148642940943036,"exchange_rate24":0.009771269246015119,"exchange_rate_vol":0.0001783261222640727,"exchange_rate_curr":"BTC","market_cap":"$0","estimated_rewards":"0.0","estimated_rewards24":"0.0","btc_revenue":"0.0","btc_revenue24":"0.0","profitability":0,"profitability24":0,"lagging":false,"timestamp":1745896143},"Nicehash-Etchash":{"id":50,"tag":"NICEHASH","algorithm":"Etchash","block_time":1,"block_reward":1,"block_reward24":1,"last_block":0,"difficulty":1,"difficulty24":1,"nethash":156768408659,"exchange_rate":7.3283511314178675e-06,"exchange_rate24":7.465360015672856e-06,"exchange_rate_vol":0.0012213248830381042,"exchange_rate_curr":"BTC","market_cap":"$0","estimated_rewards":"0.0","estimated_rewards24":"0.0","btc_revenue":"0.0","btc_revenue24":"0.0","profitability":0,"profitability24":0,"lagging":false,"timestamp":1745896142},"Larissa":{"id":398,"tag":"LRS","algorithm":"Ethash","block_time":"13.1829","block_reward":3.0058,"block_reward24":3.0057999999999723,"last_block":3157516,"difficulty":2825077921622.0,"difficulty24":2804009849020.794,"nethash":214298668852,"exchange_rate":9.593380060172234e-08,"exchange_rate24":9.57385758246172e-08,"exchange_rate_vol":0.00026562305524410084,"exchange_rate_curr":"BTC","market_cap":"$173,505","estimated_rewards":"0.0","estimated_rewards24":"0.0","btc_revenue":"0.0","btc_revenue24":"0.0","profitability":0,"profitability24":0,"lagging":false,"timestamp":1745896009},"Etica":{"id":382,"tag":"EGAZ","algorithm":"Etchash","block_time":"12.8404","block_reward":2.0,"block_reward24":2.0,"last_block":7417660,"difficulty":880013418480.0,"difficulty24":866678508243.2969,"nethash":68534735559,"exchange_rate":3.380735896425334e-08,"exchange_rate24":3.34458028094694e-08,"exchange_rate_vol":0.0002886452639400896,"exchange_rate_curr":"BTC","market_cap":"$0","estimated_rewards":"0.0","estimated_rewards24":"0.0","btc_revenue":"0.0","btc_revenue24":"0.0","profitability":0,"profitability24":0,"lagging":false,"timestamp":1745896113},"OctaSpace":{"id":361,"tag":"OCTA","algorithm":"Ethash","block_time":"12.7818","block_reward":1.2,"block_reward24":1.2000000000000124,"last_block":6978695,"difficulty":74683703112042.0,"difficulty24":70649754503485.14,"nethash":5842972281841,"exchange_rate":6.986713189766088e-06,"exchange_rate24":6.306122661289447e-06,"exchange_rate_vol":4.56526595757573,"exchange_rate_curr":"BTC","market_cap":"$23,970,842","estimated_rewards":"0.0","estimated_rewards24":"0.0","btc_revenue":"0.0","btc_revenue24":"0.0","profitability":0,"profitability24":0,"lagging":false,"timestamp":1745896110},"EthereumClassic":{"id":162,"tag":"ETC","algorithm":"Etchash","block_time":"13.7769","block_reward":1.98656,"block_reward24":1.986560000000033,"last_block":22135573,"difficulty":3.890894707782591e+15,"difficulty24":3.883993989327549e+15,"nethash":282421641137163,"exchange_rate":0.00018022272673005218,"exchange_rate24":0.00017838187428531225,"exchange_rate_vol":28.58478031548177,"exchange_rate_curr":"BTC","market_cap":"$2,585,511,457","estimated_rewards":"0.0","estimated_rewards24":"0.0","btc_revenue":"0.0","btc_revenue24":"0.0","profitability":0,"profitability24":0,"lagging":false,"timestamp":1745896090},"QuarkChain":{"id":318,"tag":"QKC","algorithm":"Ethash","block_time":"9.7628","block_reward":1.5093132820480002,"block_reward24":1.5093132820479904,"last_block":19305358,"difficulty":551091164999.0,"difficulty24":574593555907.7709,"nethash":112896129184,"exchange_rate":8.525333999681278e-08,"exchange_rate24":8.571230293289831e-08,"exchange_rate_vol":7.747449187803843,"exchange_rate_curr":"BTC","market_cap":"$0","estimated_rewards":"0.0","estimated_rewards24":"0.0","btc_revenue":"0.0","btc_revenue24":"0.0","profitability":0,"profitability24":0,"lagging":false,"timestamp":1745896107},"EthereumPoW":{"id":353,"tag":"ETHW","algorithm":"Ethash","block_time":"13.0492","block_reward":2.001416737657106,"block_reward24":2.0016402959590565,"last_block":21756007,"difficulty":326932010784348.0,"difficulty24":318398853402568.9,"nethash":25053797227749,"exchange_rate":2.0081380879924022e-05,"exchange_rate24":2.0293863064997145e-05,"exchange_rate_vol":20.095277255345806,"exchange_rate_curr":"BTC","market_cap":"$204,748,279","estimated_rewards":"0.0","estimated_rewards24":"0.0","btc_revenue":"0.0","btc_revenue24":"0.0","profitability":0,"profitability24":0,"lagging":false,"timestamp":1745896144}}}