{"coins":{"Nicehash-Ethash":{"id":15,"tag":"NICEHASH","algorithm":"Ethash","block_time":1,"block_reward":1,"block_reward24":1,"last_block":0,"difficulty":1,"difficulty24":1,"nethash":189651982495,"exchange_rate":0.030242347403260112,"exchange_rate24":0.03850932860120764,"exchange_rate_vol":0.008010695283950188,"exchange_rate_curr":"BTC","market_cap":"$0","estimated_rewards":"0.0","estimated_rewards24":"0.0","btc_revenue":"0.0","btc_revenue24":"0.0","profitability":0,"profitability24":0,"lagging":false,"timestamp":1720146851},"Nicehash-Etchash":{"id":50,"tag":"NICEHASH","algorithm":"Etchash","block_time":1,"block_reward":1,"block_reward24":1,"last_block":0,"difficulty":1,"difficulty24":1,"nethash":605823172334,"exchange_rate":2.8806912791719883e-05,"exchange_rate24":2.8244698997209746e-05,"exchange_rate_vol":0.017332858420782124,"exchange_rate_curr":"BTC","market_cap":"$0","estimated_rewards":"0.0","estimated_rewards24":"0.0","btc_revenue":"0.0","btc_revenue24":"0.0","profitability":0,"profitability24":0,"lagging":false,"timestamp":1720146851},"EtherGem":{"id":307,"tag":"EGEM","algorithm":"Ethash","block_time":"13.695","block_reward":2.88,"block_reward24":2.88000000000005,"last_block":15915811,"difficulty":109231788778.0,"difficulty24":61225608334.80645,"nethash":7976034229,"exchange_rate":7.0e-09,"exchange_rate24":7.000000000000082e-09,"exchange_rate_vol":0.0082457413803,"exchange_rate_curr":"BTC","market_cap":"$15,250","estimated_rewards":"0.0","estimated_rewards24":"0.0","btc_revenue":"0.0","btc_revenue24":"0.0","profitability":0,"profitability24":0,"lagging":false,"timestamp":1720146852},"Etica":{"id":382,"tag":"EGAZ","algorithm":"Etchash","block_time":"12.3458","block_reward":2.0,"block_reward24":2.0,"last_block":5422284,"difficulty":591403544386.0,"difficulty24":547438854421.8077,"nethash":47903217643,"exchange_rate":9.421500845224887e-08,"exchange_rate24":9.190921776875289e-08,"exchange_rate_vol":0.0010241807370066503,"exchange_rate_curr":"BTC","market_cap":"$59,892","estimated_rewards":"0.0","estimated_rewards24":"0.0","btc_revenue":"0.0","btc_revenue24":"0.0","profitability":0,"profitability24":0,"lagging":false,"timestamp":1720146873},"Larissa":{"id":398,"tag":"LRS","algorithm":"Ethash","block_time":"12.8555","block_reward":4.6693,"block_reward24":4.628761373148103,"last_block":1165727,"difficulty":7335097406230.0,"difficulty24":7454510674002.093,"nethash":570580483546,"exchange_rate":5.78500907808167e-07,"exchange_rate24":5.758434482459221e-07,"exchange_rate_vol":0.30770360330509844,"exchange_rate_curr":"BTC","market_cap":"$327,576","estimated_rewards":"0.0","estimated_rewards24":"0.0","btc_revenue":"0.0","btc_revenue24":"0.0","profitability":0,"profitability24":0,"lagging":false,"timestamp":1720146876},"Hypra":{"id":365,"tag":"HYP","algorithm":"EthashB3","block_time":"8.7553","block_reward":3.8049999999999997,"block_reward24":3.805000000000004,"last_block":3471106,"difficulty":1080418084280.0,"difficulty24":1047902267563.0216,"nethash":123401606373,"exchange_rate":2.1912913174551782e-07,"exchange_rate24":2.2925408579928592e-07,"exchange_rate_vol":0.02080899298068035,"exchange_rate_curr":"BTC","market_cap":"$0","estimated_rewards":"0.0","estimated_rewards24":"0.0","btc_revenue":"0.0","btc_revenue24":"0.0","profitability":0,"profitability24":0,"lagging":false,"timestamp":1720146747},"Bitnet BTN":{"id":378,"tag":"BTN","algorithm":"Ethash","block_time":"12.9188","block_reward":1.0,"block_reward24":1.0,"last_block":2395866,"difficulty":4965775982338.0,"difficulty24":4843337565405.236,"nethash":384383687520,"exchange_rate":1.9055469296590229e-06,"exchange_rate24":1.854117626085587e-06,"exchange_rate_vol":0.01698936060152875,"exchange_rate_curr":"BTC","market_cap":"$247,952","estimated_rewards":"0.0","estimated_rewards24":"0.0","btc_revenue":"0.0","btc_revenue24":"0.0","profitability":0,"profitability24":0,"lagging":false,"timestamp":1720146871},"Canxium":{"id":373,"tag":"CAU","algorithm":"Ethash","block_time":"8.5053","block_reward":0.1875,"block_reward24":0.1875,"last_block":4324211,"difficulty":27112821730683.0,"difficulty24":25277702535575.723,"nethash":3187756073352,"exchange_rate":4.755628068793926e-05,"exchange_rate24":4.851118770249426e-05,"exchange_rate_vol":0.04884385747630908,"exchange_rate_curr":"BTC","market_cap":"$2,273,157","estimated_rewards":"0.0","estimated_rewards24":"0.0","btc_revenue":"0.0","btc_revenue24":"0.0","profitability":0,"profitability24":0,"lagging":false,"timestamp":1720146868},"Dogether":{"id":393,"tag":"DOGETHER","algorithm":"Ethash","block_time":"18.2127","block_reward":40000.0,"block_reward24":40000.0,"last_block":987039,"difficulty":1664848995407.0,"difficulty24":1557629504254.8523,"nethash":91411432429,"exchange_rate":1.3498354515523898e-11,"exchange_rate24":1.3224889614280822e-11,"exchange_rate_vol":0.0007293565187114366,"exchange_rate_curr":"BTC","market_cap":"$0","estimated_rewards":"0.0","estimated_rewards24":"0.0","btc_revenue":"0.0","btc_revenue24":"0.0","profitability":0,"profitability24":0,"lagging":false,"timestamp":1720146874},"Etho":{"id":306,"tag":"ETHO","algorithm":"Ethash","block_time":"12.3973","block_reward":0.3,"block_reward24":0.30000000000000326,"last_block":14411513,"difficulty":148267844507.0,"difficulty24":108709879844.84114,"nethash":11959688360,"exchange_rate":1.3594771333491925e-07,"exchange_rate24":1.4029555678619275e-07,"exchange_rate_vol":0.002771966887186538,"exchange_rate_curr":"BTC","market_cap":"$605,822","estimated_rewards":"0.0","estimated_rewards24":"0.0","btc_revenue":"0.0","btc_revenue24":"0.0","profitability":0,"profitability24":0,"lagging":false,"timestamp":1720146852},"Callisto":{"id":283,"tag":"CLO","algorithm":"Ethash","block_time":"13.6953","block_reward":38.88,"block_reward24":38.577568761793046,"last_block":15113251,"difficulty":326400247564.0,"difficulty24":318054329332.22156,"nethash":23833011877,"exchange_rate":2.1211699952966126e-09,"exchange_rate24":2.0862148103405243e-09,"exchange_rate_vol":0.00038948189719723324,"exchange_rate_curr":"BTC","market_cap":"$375,677","estimated_rewards":"0.0","estimated_rewards24":"0.0","btc_revenue":"0.0","btc_revenue24":"0.0","profitability":0,"profitability24":0,"lagging":true,"timestamp":1720086133},"OctaSpace":{"id":361,"tag":"OCTA","algorithm":"Ethash","block_time":"12.8549","block_reward":1.85,"block_reward24":1.8499999999999928,"last_block":4985527,"difficulty":163374173232611.0,"difficulty24":163947628286433.22,"nethash":12709097171709,"exchange_rate":3.133721887266301e-05,"exchange_rate24":3.214900338467939e-05,"exchange_rate_vol":1.0140295118524116,"exchange_rate_curr":"BTC","market_cap":"$53,213,922","estimated_rewards":"0.0","estimated_rewards24":"0.0","btc_revenue":"0.0","btc_revenue24":"0.0","profitability":0,"profitability24":0,"lagging":false,"timestamp":1720146865},"QuarkChain":{"id":318,"tag":"QKC","algorithm":"Ethash","block_time":"9.7896","block_reward":1.7151287296,"block_reward24":1.715128729600014,"last_block":16678036,"difficulty":376999092450.0,"difficulty24":356448557212.39435,"nethash":77020326152,"exchange_rate":1.1e-07,"exchange_rate24":1.1528995756718364e-07,"exchange_rate_vol":0.6137752,"exchange_rate_curr":"BTC","market_cap":"$0","estimated_rewards":"0.0","estimated_rewards24":"0.0","btc_revenue":"0.0","btc_revenue24":"0.0","profitability":0,"profitability24":0,"lagging":false,"timestamp":1720146853},"EthereumPoW":{"id":353,"tag":"ETHW","algorithm":"Ethash","block_time":"13.3771","block_reward":2.000490382469001,"block_reward24":2.0011609718481354,"last_block":19805114,"difficulty":209278321997050.0,"difficulty24":213551016945366.28,"nethash":15644521009564,"exchange_rate":3.5604101326011736e-05,"exchange_rate24":3.790596545977871e-05,"exchange_rate_vol":25.454024507163684,"exchange_rate_curr":"BTC","market_cap":"$218,980,387","estimated_rewards":"0.0","estimated_rewards24":"0.0","btc_revenue":"0.0","btc_revenue24":"0.0","profitability":0,"profitability24":0,"lagging":false,"timestamp":1720146878},"EthereumClassic":{"id":162,"tag":"ETC","algorithm":"Etchash","block_time":"13.4561","block_reward":1.98656,"block_reward24":1.9865600000000334,"last_block":20225453,"difficulty":2.23296514239819e+15,"difficulty24":2227649246920747.8,"nethash":165944452136814,"exchange_rate":0.0003519,"exchange_rate24":0.0003696407355021218,"exchange_rate_vol":22.87469921,"exchange_rate_curr":"BTC","market_cap":"$2,966,658,392","estimated_rewards":"0.0","estimated_rewards24":"0.0","btc_revenue":"0.0","btc_revenue24":"0.0","profitability":0,"profitability24":0,"lagging":false,"timestamp":1720146855}}}