{"coins":{"Nicehash-Ethash":{"id":15,"tag":"NICEHASH","algorithm":"Ethash","block_time":1,"block_reward":1,"block_reward24":1,"last_block":0,"difficulty":1,"difficulty24":1,"nethash":391774216626,"exchange_rate":0.04296000481972834,"exchange_rate24":0.044363665402164736,"exchange_rate_vol":0.0173988678678985,"exchange_rate_curr":"BTC","market_cap":"$0","estimated_rewards":"0.0","estimated_rewards24":"0.0","btc_revenue":"0.0","btc_revenue24":"0.0","profitability":0,"profitability24":0,"lagging":false,"timestamp":1714357631},"Nicehash-Etchash":{"id":50,"tag":"NICEHASH","algorithm":"Etchash","block_time":1,"block_reward":1,"block_reward24":1,"last_block":0,"difficulty":1,"difficulty24":1,"nethash":880522954212,"exchange_rate":3.86086607781659e-05,"exchange_rate24":3.896490750163331e-05,"exchange_rate_vol":0.03430170882112995,"exchange_rate_curr":"BTC","market_cap":"$0","estimated_rewards":"0.0","estimated_rewards24":"0.0","btc_revenue":"0.0","btc_revenue24":"0.0","profitability":0,"profitability24":0,"lagging":false,"timestamp":1714357631},"EtherGem":{"id":307,"tag":"EGEM","algorithm":"Ethash","block_time":"12.3514","block_reward":2.88,"block_reward24":2.880000000000052,"last_block":15462330,"difficulty":105988412442.0,"difficulty24":98862663855.94168,"nethash":8581084933,"exchange_rate":7.0e-09,"exchange_rate24":7.002853067047156e-09,"exchange_rate_vol":0.0047896030798,"exchange_rate_curr":"BTC","market_cap":"$16,867","estimated_rewards":"0.0","estimated_rewards24":"0.0","btc_revenue":"0.0","btc_revenue24":"0.0","profitability":0,"profitability24":0,"lagging":false,"timestamp":1714357591},"Etho":{"id":306,"tag":"ETHO","algorithm":"Ethash","block_time":"14.2667","block_reward":0.3,"block_reward24":0.3000000000000032,"last_block":13966270,"difficulty":79484505250.0,"difficulty24":109062043711.6567,"nethash":5571330808,"exchange_rate":1.2e-07,"exchange_rate24":1.1931526390870227e-07,"exchange_rate_vol":0.0,"exchange_rate_curr":"BTC","market_cap":"$591,451","estimated_rewards":"0.0","estimated_rewards24":"0.0","btc_revenue":"0.0","btc_revenue24":"0.0","profitability":0,"profitability24":0,"lagging":false,"timestamp":1714357594},"Hypra":{"id":365,"tag":"HYP","algorithm":"EthashB3","block_time":"8.8783","block_reward":3.8049999999999997,"block_reward24":3.805000000000003,"last_block":2808601,"difficulty":2164076724307.0,"difficulty24":2398605343829.8594,"nethash":243748997477,"exchange_rate":2.8530241552019276e-07,"exchange_rate24":3.611114756246299e-07,"exchange_rate_vol":0.03476419463592848,"exchange_rate_curr":"BTC","market_cap":"$0","estimated_rewards":"0.0","estimated_rewards24":"0.0","btc_revenue":"0.0","btc_revenue24":"0.0","profitability":0,"profitability24":0,"lagging":false,"timestamp":1714357354},"OctaSpace":{"id":361,"tag":"OCTA","algorithm":"Ethash","block_time":"12.5393","block_reward":1.85,"block_reward24":1.8499999999999932,"last_block":4535749,"difficulty":78161641384557.0,"difficulty24":72455193166225.6,"nethash":6233333709581,"exchange_rate":1.810689152348951e-05,"exchange_rate24":1.798419588036333e-05,"exchange_rate_vol":0.19781997302628088,"exchange_rate_curr":"BTC","market_cap":"$31,902,974","estimated_rewards":"0.0","estimated_rewards24":"0.0","btc_revenue":"0.0","btc_revenue24":"0.0","profitability":0,"profitability24":0,"lagging":false,"timestamp":1714357598},"EthereumPoW":{"id":353,"tag":"ETHW","algorithm":"Ethash","block_time":"13.0555","block_reward":2.001644124596004,"block_reward24":2.004083296873242,"last_block":19367485,"difficulty":243244791522644.0,"difficulty24":238687167747292.5,"nethash":18631595229799,"exchange_rate":6.378780194002409e-05,"exchange_rate24":6.369668346177746e-05,"exchange_rate_vol":10.783015619081024,"exchange_rate_curr":"BTC","market_cap":"$433,917,561","estimated_rewards":"0.0","estimated_rewards24":"0.0","btc_revenue":"0.0","btc_revenue24":"0.0","profitability":0,"profitability24":0,"lagging":false,"timestamp":1714357666},"QuarkChain":{"id":318,"tag":"QKC","algorithm":"Ethash","block_time":"9.7678","block_reward":1.7151287296,"block_reward24":1.715128729600013,"last_block":16088249,"difficulty":395635916036.0,"difficulty24":373776573382.08594,"nethash":81008193459,"exchange_rate":1.9e-07,"exchange_rate24":1.9384352773826556e-07,"exchange_rate_vol":0.11735613999203189,"exchange_rate_curr":"BTC","market_cap":"$0","estimated_rewards":"0.0","estimated_rewards24":"0.0","btc_revenue":"0.0","btc_revenue24":"0.0","profitability":0,"profitability24":0,"lagging":false,"timestamp":1714357592},"Callisto":{"id":283,"tag":"CLO","algorithm":"Ethash","block_time":"13.1535","block_reward":38.88,"block_reward24":38.53956854713054,"last_block":14669161,"difficulty":298492316052.0,"difficulty24":309334628093.71014,"nethash":22692995480,"exchange_rate":3.745324288340835e-09,"exchange_rate24":3.7155805523544748e-09,"exchange_rate_vol":0.23505698729834212,"exchange_rate_curr":"BTC","market_cap":"$733,657","estimated_rewards":"0.0","estimated_rewards24":"0.0","btc_revenue":"0.0","btc_revenue24":"0.0","profitability":0,"profitability24":0,"lagging":false,"timestamp":1714356978},"EthereumClassic":{"id":162,"tag":"ETC","algorithm":"Etchash","block_time":"13.3039","block_reward":2.4832,"block_reward24":2.4831999999999628,"last_block":19792533,"difficulty":2.327206693353422e+15,"difficulty24":2.278006110631519e+15,"nethash":174926652587092,"exchange_rate":0.0004467,"exchange_rate24":0.0004526581792318632,"exchange_rate_vol":43.97559143,"exchange_rate_curr":"BTC","market_cap":"$4,136,922,801","estimated_rewards":"0.0","estimated_rewards24":"0.0","btc_revenue":"0.0","btc_revenue24":"0.0","profitability":0,"profitability24":0,"lagging":false,"timestamp":1714357585}}}