{"coins":{"Nicehash-Etchash":{"id":50,"tag":"NICEHASH","algorithm":"Etchash","block_time":1,"block_reward":1,"block_reward24":1,"last_block":0,"difficulty":1,"difficulty24":1,"nethash":1020884312456,"exchange_rate":6.396256586078749e-05,"exchange_rate24":6.57516132373258e-05,"exchange_rate_vol":0.06706219737767034,"exchange_rate_curr":"BTC","market_cap":"$0","estimated_rewards":"0.0","estimated_rewards24":"0.0","btc_revenue":"0.0","btc_revenue24":"0.0","profitability":0,"profitability24":0,"lagging":false,"timestamp":1705890920},"Nicehash-Ethash":{"id":15,"tag":"NICEHASH","algorithm":"Ethash","block_time":1,"block_reward":1,"block_reward24":1,"last_block":0,"difficulty":1,"difficulty24":1,"nethash":1189807962691,"exchange_rate":0.11445061546997536,"exchange_rate24":0.10995492222273084,"exchange_rate_vol":0.12264405508998796,"exchange_rate_curr":"BTC","market_cap":"$0","estimated_rewards":"0.0","estimated_rewards24":"0.0","btc_revenue":"0.0","btc_revenue24":"0.0","profitability":0,"profitability24":0,"lagging":false,"timestamp":1705890919},"Etho":{"id":306,"tag":"ETHO","algorithm":"Ethash","block_time":"12.8241","block_reward":0.3,"block_reward24":0.30000000000000326,"last_block":13312305,"difficulty":41743327405.0,"difficulty24":40911503057.24965,"nethash":3255068769,"exchange_rate":3.4e-08,"exchange_rate24":3.316312056737582e-08,"exchange_rate_vol":0.0,"exchange_rate_curr":"BTC","market_cap":"$109,791","estimated_rewards":"0.0","estimated_rewards24":"0.0","btc_revenue":"0.0","btc_revenue24":"0.0","profitability":0,"profitability24":0,"lagging":false,"timestamp":1705890861},"EtherGem":{"id":307,"tag":"EGEM","algorithm":"Ethash","block_time":"12.3893","block_reward":2.88,"block_reward24":2.8800000000000523,"last_block":14784815,"difficulty":46024211188.0,"difficulty24":64484575821.93918,"nethash":3714835478,"exchange_rate":1.5e-08,"exchange_rate24":1.5539007092198838e-08,"exchange_rate_vol":0.0026024368944,"exchange_rate_curr":"BTC","market_cap":"$23,680","estimated_rewards":"0.0","estimated_rewards24":"0.0","btc_revenue":"0.0","btc_revenue24":"0.0","profitability":0,"profitability24":0,"lagging":false,"timestamp":1705890862},"Hypra":{"id":365,"tag":"HYP","algorithm":"EthashB3","block_time":"8.6964","block_reward":3.8049999999999997,"block_reward24":3.805000000000006,"last_block":1832015,"difficulty":5672420513627.0,"difficulty24":5575985391622.083,"nethash":652272263652,"exchange_rate":1.7466698374436506e-06,"exchange_rate24":1.7411207434326535e-06,"exchange_rate_vol":0.004459185678909962,"exchange_rate_curr":"BTC","market_cap":"$0","estimated_rewards":"0.0","estimated_rewards24":"0.0","btc_revenue":"0.0","btc_revenue24":"0.0","profitability":0,"profitability24":0,"lagging":false,"timestamp":1705890521},"OctaSpace":{"id":361,"tag":"OCTA","algorithm":"Ethash","block_time":"12.2594","block_reward":2.3,"block_reward24":2.2999999999999714,"last_block":3876273,"difficulty":49548153250576.0,"difficulty24":44189403895287.83,"nethash":4041645859550,"exchange_rate":1.4628958612651208e-05,"exchange_rate24":1.468584660185939e-05,"exchange_rate_vol":0.4881574404905668,"exchange_rate_curr":"BTC","market_cap":"$15,943,706","estimated_rewards":"0.0","estimated_rewards24":"0.0","btc_revenue":"0.0","btc_revenue24":"0.0","profitability":0,"profitability24":0,"lagging":false,"timestamp":1705890869},"EthereumFair":{"id":355,"tag":"ETHF","algorithm":"Ethash","block_time":"12.888","block_reward":1.0,"block_reward24":1.0000454099636633,"last_block":18789502,"difficulty":5623927087268.0,"difficulty24":5870987203783.542,"nethash":436369264995,"exchange_rate":4.342480686242586e-06,"exchange_rate24":4.323100980665622e-06,"exchange_rate_vol":0.3394775912065613,"exchange_rate_curr":"BTC","market_cap":"$0","estimated_rewards":"0.0","estimated_rewards24":"0.0","btc_revenue":"0.0","btc_revenue24":"0.0","profitability":0,"profitability24":0,"lagging":false,"timestamp":1705890742},"QuarkChain":{"id":318,"tag":"QKC","algorithm":"Ethash","block_time":"10.1898","block_reward":1.94900992,"block_reward24":1.9490099199999849,"last_block":15226373,"difficulty":186447842146.0,"difficulty24":280183773756.9929,"nethash":36594995416,"exchange_rate":2.4e-07,"exchange_rate24":2.40000000000002e-07,"exchange_rate_vol":0.91001039,"exchange_rate_curr":"BTC","market_cap":"$0","estimated_rewards":"0.0","estimated_rewards24":"0.0","btc_revenue":"0.0","btc_revenue24":"0.0","profitability":0,"profitability24":0,"lagging":false,"timestamp":1705890857},"EthereumClassic":{"id":162,"tag":"ETC","algorithm":"Etchash","block_time":"13.4419","block_reward":2.4832,"block_reward24":2.4831999999999623,"last_block":19159673,"difficulty":1.867529318446887e+15,"difficulty24":1904515316905151.5,"nethash":138933433402040,"exchange_rate":0.0005805,"exchange_rate24":0.0005939421499292794,"exchange_rate_vol":25.58195907,"exchange_rate_curr":"BTC","market_cap":"$3,483,019,896","estimated_rewards":"0.0","estimated_rewards24":"0.0","btc_revenue":"0.0","btc_revenue24":"0.0","profitability":0,"profitability24":0,"lagging":false,"timestamp":1705890850},"EthereumPoW":{"id":353,"tag":"ETHW","algorithm":"Ethash","block_time":"13.3654","block_reward":2.0053251154986644,"block_reward24":2.006611019355972,"last_block":18729710,"difficulty":166552817404951.0,"difficulty24":167386486518211.97,"nethash":12461491418509,"exchange_rate":6.5966999082152e-05,"exchange_rate24":6.737572758896264e-05,"exchange_rate_vol":20.30250279410303,"exchange_rate_curr":"BTC","market_cap":"$294,000,846","estimated_rewards":"0.0","estimated_rewards24":"0.0","btc_revenue":"0.0","btc_revenue24":"0.0","profitability":0,"profitability24":0,"lagging":false,"timestamp":1705890896},"Callisto":{"id":283,"tag":"CLO","algorithm":"Ethash","block_time":"13.1809","block_reward":38.88,"block_reward24":38.64715216055008,"last_block":14014677,"difficulty":1006419162135.0,"difficulty24":1058104279969.4417,"nethash":76354358362,"exchange_rate":1.8642426834643657e-08,"exchange_rate24":1.8178856814928957e-08,"exchange_rate_vol":0.4708986926776341,"exchange_rate_curr":"BTC","market_cap":"$2,392,538","estimated_rewards":"0.0","estimated_rewards24":"0.0","btc_revenue":"0.0","btc_revenue24":"0.0","profitability":0,"profitability24":0,"lagging":false,"timestamp":1705890733}}}