{"coins":{"Nicehash-Etchash":{"id":50,"tag":"NICEHASH","algorithm":"Etchash","block_time":1,"block_reward":1,"block_reward24":1,"last_block":0,"difficulty":1,"difficulty24":1,"nethash":1080413724855,"exchange_rate":5.246163687891249e-05,"exchange_rate24":5.498925425016e-05,"exchange_rate_vol":0.060313340539686275,"exchange_rate_curr":"BTC","market_cap":"$0","estimated_rewards":"0.0","estimated_rewards24":"0.0","btc_revenue":"0.0","btc_revenue24":"0.0","profitability":0,"profitability24":0,"lagging":false,"timestamp":1700792833},"Nicehash-Ethash":{"id":15,"tag":"NICEHASH","algorithm":"Ethash","block_time":1,"block_reward":1,"block_reward24":1,"last_block":0,"difficulty":1,"difficulty24":1,"nethash":2289749179368,"exchange_rate":0.19547158928620278,"exchange_rate24":0.1413486069533717,"exchange_rate_vol":0.21784100830743588,"exchange_rate_curr":"BTC","market_cap":"$0","estimated_rewards":"0.0","estimated_rewards24":"0.0","btc_revenue":"0.0","btc_revenue24":"0.0","profitability":0,"profitability24":0,"lagging":false,"timestamp":1700792833},"OctaSpace":{"id":361,"tag":"OCTA","algorithm":"Ethash","block_time":"12.9842","block_reward":2.3,"block_reward24":2.299999999999972,"last_block":3481571,"difficulty":48402800708752.0,"difficulty24":49496168438863.23,"nethash":3727823101057,"exchange_rate":2.508410379466911e-05,"exchange_rate24":2.312715359514138e-05,"exchange_rate_vol":2.7947413989754666,"exchange_rate_curr":"BTC","market_cap":"$22,865,290","estimated_rewards":"0.0","estimated_rewards24":"0.0","btc_revenue":"0.0","btc_revenue24":"0.0","profitability":0,"profitability24":0,"lagging":false,"timestamp":1700792814},"Etho":{"id":306,"tag":"ETHO","algorithm":"Ethash","block_time":"13.371","block_reward":0.3,"block_reward24":0.3000000000000032,"last_block":12918624,"difficulty":108082593875.0,"difficulty24":105417362132.93448,"nethash":8083359051,"exchange_rate":5.1e-08,"exchange_rate24":5.099999999999953e-08,"exchange_rate_vol":0.0017291161089,"exchange_rate_curr":"BTC","market_cap":"$149,031","estimated_rewards":"0.0","estimated_rewards24":"0.0","btc_revenue":"0.0","btc_revenue24":"0.0","profitability":0,"profitability24":0,"lagging":false,"timestamp":1700792806},"EtherGem":{"id":307,"tag":"EGEM","algorithm":"Ethash","block_time":"11.9299","block_reward":2.88,"block_reward24":2.8800000000000514,"last_block":14370621,"difficulty":147674616625.0,"difficulty24":119145710420.37822,"nethash":12378529294,"exchange_rate":2.7e-08,"exchange_rate24":2.6881258941345017e-08,"exchange_rate_vol":0.0462688392548,"exchange_rate_curr":"BTC","market_cap":"$38,572","estimated_rewards":"0.0","estimated_rewards24":"0.0","btc_revenue":"0.0","btc_revenue24":"0.0","profitability":0,"profitability24":0,"lagging":false,"timestamp":1700792801},"EthereumPoW":{"id":353,"tag":"ETHW","algorithm":"Ethash","block_time":"13.3326","block_reward":2.0044209780243647,"block_reward24":2.011074160284143,"last_block":18348065,"difficulty":138325820123381.0,"difficulty24":136426552172385.73,"nethash":10375007134645,"exchange_rate":4.461564619303344e-05,"exchange_rate24":4.3038344477666414e-05,"exchange_rate_vol":5.880192855646502,"exchange_rate_curr":"BTC","market_cap":"$179,939,127","estimated_rewards":"0.0","estimated_rewards24":"0.0","btc_revenue":"0.0","btc_revenue24":"0.0","profitability":0,"profitability24":0,"lagging":false,"timestamp":1700792832},"EthereumFair":{"id":355,"tag":"ETHF","algorithm":"Ethash","block_time":"12.6105","block_reward":1.0,"block_reward24":1.0000770584109027,"last_block":18391609,"difficulty":10844160620817.0,"difficulty24":10619100848268.193,"nethash":859931059102,"exchange_rate":7.862341389760401e-06,"exchange_rate24":7.1353400051626755e-06,"exchange_rate_vol":1.136707549149017,"exchange_rate_curr":"BTC","market_cap":"$0","estimated_rewards":"0.0","estimated_rewards24":"0.0","btc_revenue":"0.0","btc_revenue24":"0.0","profitability":0,"profitability24":0,"lagging":false,"timestamp":1700792662},"Callisto":{"id":283,"tag":"CLO","algorithm":"Ethash","block_time":"12.7198","block_reward":38.88,"block_reward24":38.72973411608736,"last_block":13619671,"difficulty":1331908961295.0,"difficulty24":1303181753094.074,"nethash":104711470407,"exchange_rate":1.8063869694189406e-08,"exchange_rate24":1.8361350256708396e-08,"exchange_rate_vol":0.8033301636581781,"exchange_rate_curr":"BTC","market_cap":"$2,097,895","estimated_rewards":"0.0","estimated_rewards24":"0.0","btc_revenue":"0.0","btc_revenue24":"0.0","profitability":0,"profitability24":0,"lagging":false,"timestamp":1700792799},"QuarkChain":{"id":318,"tag":"QKC","algorithm":"Ethash","block_time":"9.714","block_reward":1.94900992,"block_reward24":1.9490099199999849,"last_block":14706524,"difficulty":478399519249.0,"difficulty24":448466860573.09546,"nethash":98496915637,"exchange_rate":2.9e-07,"exchange_rate24":2.915931721194916e-07,"exchange_rate_vol":3.68586873,"exchange_rate_curr":"BTC","market_cap":"$0","estimated_rewards":"0.0","estimated_rewards24":"0.0","btc_revenue":"0.0","btc_revenue24":"0.0","profitability":0,"profitability24":0,"lagging":false,"timestamp":1700792806},"EthereumClassic":{"id":162,"tag":"ETC","algorithm":"Etchash","block_time":"13.3576","block_reward":2.4832,"block_reward24":2.4831999999999628,"last_block":18778574,"difficulty":2.029585029380648e+15,"difficulty24":2018099116306197.2,"nethash":151942342140852,"exchange_rate":0.00050695,"exchange_rate24":0.0005069932432432445,"exchange_rate_vol":11.03770543,"exchange_rate_curr":"BTC","market_cap":"$2,734,025,305","estimated_rewards":"0.0","estimated_rewards24":"0.0","btc_revenue":"0.0","btc_revenue24":"0.0","profitability":0,"profitability24":0,"lagging":false,"timestamp":1700792795},"Ubiq":{"id":173,"tag":"UBQ","algorithm":"Ubqhash","block_time":"21.0","block_reward":1.5,"block_reward24":1.5,"last_block":4578997,"difficulty":241360098460.0,"difficulty24":245326648867.09482,"nethash":11493338021,"exchange_rate":8.0e-08,"exchange_rate24":7.786628733997087e-08,"exchange_rate_vol":0.00717949,"exchange_rate_curr":"BTC","market_cap":"$127,507","estimated_rewards":"0.0","estimated_rewards24":"0.0","btc_revenue":"0.0","btc_revenue24":"0.0","profitability":0,"profitability24":0,"lagging":false,"timestamp":1700792795}}}